{
	"pages": [
        {
            "path": "pages/login/login"
        },
        {
            "path": "pages/index/index",
            "style": {
                "navigationBarTextStyle": "white"
            }
        },
        {
            "path": "pages/register/register"
        },
        {
            "path": "pages/company/company"
        },
		{
			"path": "pages/task-distribution/index/index"
		},
		{
			"path": "pages/task-distribution/newly/newly"
		},
		{
			"path": "pages/task-distribution/inform/inform"
		},
		{
			"path": "pages/material/outbound/outbound"
		},
		{
			"path": "pages/material/apply/apply"
		},
		{
			"path": "pages/material/give-back/give-back"
		},
		{
			"path": "pages/material/archive/archive"
		},

		{
			"path": "pages/attendance/attendance"
		},
		{
			"path": "pages/attendanceManagement/manage/manage"
        },
        // 人员管理
		{
			"path": "pages/personnel/manage/manage"
        },
        // 项目管理
		{
			"path": "pages/project/details/details"
        },
		{
			"path": "pages/project/modify/modify"
        },
        {
			"path": "pages/project/newly/newly"
		},
		{
            "path": "pages/project/manage/manage",
            "style": {
                "enablePullDownRefresh": true
            }
        },
        // 添加新建单位
        {
            "path": "pages/participation/construction/construction",
            "style":{
                "enablePullDownRefresh":true
            }
        },
		{
			"path": "pages/participation/add/add"
        },
        // 合同管理
        {
            "path": "pages/contract/manage/manage",
            "style": {
                "enablePullDownRefresh": true
            }
		},
        {
            "path": "pages/contract/newly/newly"
        },
        // 发票管理
		{
			"path": "pages/invoices/manage/manage"
        },
		{
			"path": "pages/invoices/newly/newly"
        },
		{
			"path": "pages/invoices/detail/detail"
        },
        // 安全管理
		{
			"path": "pages/security/manage/manage"
		},
		{
			"path": "pages/security/detail/detail"
        },
        //零星采购
        {
            "path": "pages/purchase/list/list"
        },{
            "path": "pages/purchase/detail/detail"
        },
        //成本管理
        {
            "path": "pages/costcontrol/manage/manage"
        },
        // 工资管理
        {
            "path":"pages/wages/manage/manage"
        },
        // 新建管理
        {
            "path":"pages/journal/manage/manage"
        },
        {
            "path":"pages/journal/newly/newly"
        },
        {
            "path":"pages/journal/detail/detail"
        },
        // 费用审批
		{
            "path" : "pages/audit/materialProcurement/materialProcurement"
        },
		{
            "path" : "pages/audit/costApproval/costApproval"
		},
		{
            "path" : "pages/audit/projectPaymentApproval/projectPaymentApproval"
        },
		{
            "path" : "pages/audit/lease/lease"
        },
		{
            "path" : "pages/audit/loanApplication/loanApplication"
        },
		{
            "path" : "pages/audit/procurement/procurement"
        },
		{
            "path" : "pages/audit/businessCosts/businessCosts"
        },
        // 巡检管理
        {
            "path" : "pages/patrol/index/index"
        },
        {
            "path" : "pages/patrol/newly/newly"
        },
        {
            "path" : "pages/patrol/inform/inform"
        },
        // 权限设置
        {
            "path": "pages/jurisdiction/manage/manage"
        },
        {
            "path": "pages/jurisdiction/modify/modify"
        },

        // 工具管理
        {
            "path": "pages/two_tool/one"
        },
        {
            "path": "pages/two_tool/two"
        },
        {
            "path": "pages/two_tool/three"
        },
        {
            "path": "pages/two_tool/four"
        },
        // 简单测试
        {
            "path" : "pages/test/test"
        }
        
    ],
	"globalStyle": {
		"navigationBarTextStyle": "black",
		"navigationBarTitleText": "uni-app",
		"navigationBarBackgroundColor": "#fff",
        "backgroundColor": "#F8F8F8",
        "navigationStyle": "custom"
	},
	"condition" : {
		"current": 2,
		"list": [
            {
                "name": "主入口",
				"path": "pages/login/login",
				"query": ""
			},
            {
                "name": "项目",
                "path": "pages/company/company",
                "query": "project_id=001577721280335cd75c7854fd64848b774b59370ffae37&title=ee"
            },
            {
                "name": "项目2",
                "path": "pages/invoices/newly/newly",
                "query": "id=0015777610868424725a466cad34f8da90e66a031423d80"
            }
		]
	}
}
